[
  {
    "pal": ["#D09875", "#A76F55", "#CC6C4F", "#EF6647", "#70757B", "#9F9DA5", "#F1A066", "#988A82"],
    "bg": ["#383A3A"]
  },
  {
    "pal": ["#F0AC9E", "#5A76A6", "#D18C79", "#779AC9", "#A5726F", "#6C4E63", "#F8C4B2", "#9C8096"],
    "bg": ["#402C3D"]
  },
  {
    "pal": ["#90663C", "#D99660", "#FCCC24", "#F2A858"],
    "bg": ["#FDD781"]
  },
  {
    "pal": ["#36263B", "#CE3233", "#A75244", "#0D68AA", "#AD987F", "#EBD868"],
    "bg": ["#0F1216"]
  },
  {
    "pal": ["#3E2637", "#A65946", "#AD958C", "#C4795B"],
    "bg": ["#AD2A2B"]
  },
  {
    "pal": ["#44312B", "#A89B7D", "#9E7353", "#D19C81"],
    "bg": ["#F1C27C"]
  },
  {
    "pal": ["#4A443F", "#CDAC9D", "#D9C1B1", "#A06F63", "#B1917E", "#A89D99"],
    "bg": ["#CADCE8"]
  },
  {
    "pal": ["#3E3735", "#ADA5A2", "#9D7666", "#A28D82", "#ECC5AF", "#CD957D"],
    "bg": ["#5F5754"]
  },
  {
    "pal": ["#5D2B23", "#99463A", "#A69080", "#AAA4A3", "#BABAC0", "#CA7D75"],
    "bg": ["#0F100E"]
  },
  {
    "pal": ["#373736", "#63A2AA", "#A06C5B", "#CCF1AC", "#8A9880"],
    "bg": ["#E8919B"]
  },
  {
    "pal": ["#A4776A", "#614945", "#CA907D", "#E7C0B5", "#DD987D"],
    "bg": ["#C5DFE9"]
  },
  {
    "pal": ["#FAEDF3", "#433631", "#F9DCEA", "#E59781", "#E3D2CD"],
    "bg": ["#312722"]
  },
  {
    "pal": ["#2F292E", "#F5F9FD", "#EEF5FD", "#E9EEFD", "#76453A", "#FBE84C", "#6F6F6D", "#CDA592", "#D7AF99", "#C38070", "#B2806C", "#954F43", "#9FD1CE", "#AFF1EC", "#A57162", "#996F58", "#C5957E", "#80B5F9", "#A39964", "#F7DE44"],
    "bg": ["#DDE6FA"]
  },
  {
    "pal": ["#1D2528", "#B01B21", "#991D23", "#781F23", "#6C556B", "#C22E2E", "#A36168", "#B27250", "#D16157", "#B29372"],
    "bg": ["#6A1C23"]
  },
  {
    "pal": ["#453938", "#724742", "#786E54", "#9D675F", "#62646F", "#61649A", "#80908F", "#A89674", "#E7DED6", "#CFAE9B"],
    "bg": ["#DDE2E6"]
  },
  {
    "pal": ["#544E4E", "#777373", "#989392", "#6D5956", "#706660", "#9F766D", "#B0A6A1", "#84938C", "#D3CBC9", "#C19D87"],
    "bg": ["#2F2D2D"]
  },
  {
    "pal": ["#413345", "#705F6E", "#564071", "#7A5E98", "#A18470", "#E1D2E0", "#D3A791", "#A59BA8", "#9678AB"],
    "bg": ["#DEDEE6"]
  },
  {
    "pal": ["#2E2213", "#F1A648", "#D69A59", "#E57C3E", "#744A21", "#A5652A", "#80683C", "#D05821", "#C67732"],
    "bg": ["#D09C4B"]
  },
  {
    "pal": ["#30273F", "#3D4B76", "#527696", "#646171", "#F6F7F1", "#5E60A1", "#6F93AB", "#D2A684", "#9F7C79"],
    "bg": ["#41316B"]
  },
  {
    "pal": ["#302B2A", "#73634C", "#3B526F", "#CFA98B", "#9B7857", "#A9996C", "#ECCEB0", "#667D9E", "#DBCF97"],
    "bg": ["#1E4366"]
  },
  {
    "pal": ["#3C6844", "#9AB47A", "#A36C4E", "#93BD7E", "#609B68", "#CD6A44", "#F7C0AD"],
    "bg": ["#ED96A0"]
  }
]
